<?xml version="1.0" encoding="utf-8"?>
<TextureAtlas imagePath="logoBumpin.png">
	<!-- Created with Adobe Animate version 22.0.3.179 -->
	<!-- http://www.adobe.com/products/animate.html -->
	<SubTexture name="logo bumpin0000" x="0" y="0" width="732" height="691" frameX="-18" frameY="-15" frameWidth="769" frameHeight="726"/>
	<SubTexture name="logo bumpin0001" x="732" y="0" width="769" height="726"/>
	<SubTexture name="logo bumpin0002" x="732" y="0" width="769" height="726"/>
	<SubTexture name="logo bumpin0003" x="0" y="726" width="746" height="705" frameX="-11" frameY="-9" frameWidth="769" frameHeight="726"/>
	<SubTexture name="logo bumpin0004" x="0" y="726" width="746" height="705" frameX="-11" frameY="-9" frameWidth="769" frameHeight="726"/>
	<SubTexture name="logo bumpin0005" x="746" y="726" width="740" height="699" frameX="-14" frameY="-12" frameWidth="769" frameHeight="726"/>
	<SubTexture name="logo bumpin0006" x="746" y="726" width="740" height="699" frameX="-14" frameY="-12" frameWidth="769" frameHeight="726"/>
	<SubTexture name="logo bumpin0007" x="746" y="726" width="740" height="699" frameX="-14" frameY="-12" frameWidth="769" frameHeight="726"/>
	<SubTexture name="logo bumpin0008" x="746" y="726" width="740" height="699" frameX="-14" frameY="-12" frameWidth="769" frameHeight="726"/>
	<SubTexture name="logo bumpin0009" x="746" y="726" width="740" height="699" frameX="-14" frameY="-12" frameWidth="769" frameHeight="726"/>
	<SubTexture name="logo bumpin0010" x="746" y="726" width="740" height="699" frameX="-14" frameY="-12" frameWidth="769" frameHeight="726"/>
	<SubTexture name="logo bumpin0011" x="746" y="726" width="740" height="699" frameX="-14" frameY="-12" frameWidth="769" frameHeight="726"/>
	<SubTexture name="logo bumpin0012" x="746" y="726" width="740" height="699" frameX="-14" frameY="-12" frameWidth="769" frameHeight="726"/>
	<SubTexture name="logo bumpin0013" x="746" y="726" width="740" height="699" frameX="-14" frameY="-12" frameWidth="769" frameHeight="726"/>
	<SubTexture name="logo bumpin0014" x="746" y="726" width="740" height="699" frameX="-14" frameY="-12" frameWidth="769" frameHeight="726"/>
</TextureAtlas>